edq_quizcomp-0.4.1.dist-info/licenses/LICENSE
quizcomp/__init__.py
quizcomp/args.py
quizcomp/common.py
quizcomp/constants.py
quizcomp/group.py
quizcomp/katex.py
quizcomp/latex.py
quizcomp/log.py
quizcomp/pdf.py
quizcomp/project.py
quizcomp/quiz.py
quizcomp/variant.py
quizcomp/cli/__init__.py
quizcomp/cli/__main__.py
quizcomp/cli/canvas/__init__.py
quizcomp/cli/canvas/__main__.py
quizcomp/cli/canvas/upload.py
quizcomp/cli/gradescope/__init__.py
quizcomp/cli/gradescope/__main__.py
quizcomp/cli/gradescope/upload.py
quizcomp/cli/parse/__init__.py
quizcomp/cli/parse/__main__.py
quizcomp/cli/parse/file.py
quizcomp/cli/parse/question.py
quizcomp/cli/parse/quiz-for-testing.py
quizcomp/cli/parse/quiz.py
quizcomp/cli/pdf/__init__.py
quizcomp/cli/pdf/__main__.py
quizcomp/cli/pdf/create.py
quizcomp/cli/project/__init__.py
quizcomp/cli/project/__main__.py
quizcomp/cli/project/read.py
quizcomp/cli/qti/__init__.py
quizcomp/cli/qti/__main__.py
quizcomp/cli/qti/create.py
quizcomp/converter/__init__.py
quizcomp/converter/convert.py
quizcomp/converter/converter.py
quizcomp/converter/html.py
quizcomp/converter/json.py
quizcomp/converter/qti.py
quizcomp/converter/template.py
quizcomp/converter/tex.py
quizcomp/data/templates/edq-html/essay.template
quizcomp/data/templates/edq-html/fill_in_multiple_blanks.template
quizcomp/data/templates/edq-html/fill_in_the_blank.template
quizcomp/data/templates/edq-html/group.template
quizcomp/data/templates/edq-html/matching.template
quizcomp/data/templates/edq-html/multiple_answers.template
quizcomp/data/templates/edq-html/multiple_choice.template
quizcomp/data/templates/edq-html/multiple_dropdowns.template
quizcomp/data/templates/edq-html/numerical.template
quizcomp/data/templates/edq-html/question-separator.template
quizcomp/data/templates/edq-html/quiz.template
quizcomp/data/templates/edq-html/short_answer.template
quizcomp/data/templates/edq-html/text_only.template
quizcomp/data/templates/edq-html/true_false.template
quizcomp/data/templates/edq-html/partials/question.template
edq_quizcomp-0.4.1.dist-info/METADATA
edq_quizcomp-0.4.1.dist-info/WHEEL
edq_quizcomp-0.4.1.dist-info/top_level.txt
edq_quizcomp-0.4.1.dist-info/RECORD
