Metadata-Version: 2.4
Name: edq-quizcomp
Version: 0.4.1
Summary: A tool that can generate multiple types of quizzes from a common configuration.
Author-email: Eriq Augustine <eriq@edulinq.org>
License: MIT License
Project-URL: Homepage, https://github.com/edulinq/quiz-composer
Project-URL: Repository, https://github.com/edulinq/quiz-composer
Keywords: education,quiz,canvas,tex,latex,qti
Classifier: Intended Audience :: Education
Classifier: License :: OSI Approved :: MIT License
Classifier: Programming Language :: Python :: 3.9
Requires-Python: >=3.9
License-File: LICENSE
Requires-Dist: GitPython>=3.1
Requires-Dist: Jinja2>=3.1.0
Requires-Dist: beautifulsoup4>=4.10
Requires-Dist: lxml>=5.3.0
Requires-Dist: json5>=0.9.14
Requires-Dist: markdown-it-py>=3.0.0
Requires-Dist: mdformat>=0.7.19
Requires-Dist: mdformat_tables>=1.0.0
Requires-Dist: mdit-py-plugins>=0.4.2
Requires-Dist: requests>=2.31.0
Provides-Extra: dev
Requires-Dist: build; extra == "dev"
Requires-Dist: packaging>=21.3; extra == "dev"
Requires-Dist: twine; extra == "dev"
Requires-Dist: vermin; extra == "dev"
Dynamic: license-file
